pytokenjoin/__init__.py
pytokenjoin/edit/__init__.py
pytokenjoin/edit/join_delta.py
pytokenjoin/edit/join_knn.py
pytokenjoin/edit/join_topk.py
pytokenjoin/edit/join_utils.py
pytokenjoin/jaccard/__init__.py
pytokenjoin/jaccard/join_delta.py
pytokenjoin/jaccard/join_knn.py
pytokenjoin/jaccard/join_topk.py
pytokenjoin/jaccard/join_utils.py
pytokenjoin/utils/__init__.py
pytokenjoin/utils/utils.py
pytokenjoin/utils/verification.py
pytokenjoin-0.1.6.dist-info/LICENSE.md
pytokenjoin-0.1.6.dist-info/METADATA
pytokenjoin-0.1.6.dist-info/WHEEL
pytokenjoin-0.1.6.dist-info/top_level.txt
pytokenjoin-0.1.6.dist-info/RECORD
